udp_client.cpython-310-x86_64-linux-gnu.so
networking_udp_client-0.3.dist-info/METADATA
networking_udp_client-0.3.dist-info/top_level.txt
networking_udp_client-0.3.dist-info/RECORD
networking_udp_client-0.3.dist-info/WHEEL
