Metadata-Version: 2.1
Name: networking-udp-client
Version: 0.3
Summary: Extension providing a basic udp client for making connections, receiving and sending packets in C.
Home-page: https://github.com/lstuma/udp_client/
Author: lstuma
Author-email: g.lstuma@gmail.com
